moocxing/__init__.py
moocxing/package/MOOCXING.py
moocxing/package/MXMedia.py
moocxing/package/MXMqtt.py
moocxing/package/MXNLP.py
moocxing/package/MXPinyin.py
moocxing/package/MXSerial.py
moocxing/package/MXSpeech.py
moocxing/package/__init__.py
moocxing/plugins/__init__.py
moocxing/plugins/chat.py
moocxing/plugins/echo.py
moocxing/plugins/isTime.py
moocxing/plugins/music.py
moocxing/plugins/play.py
moocxing/plugins/weather.py
moocxing/plugins/sdk/AbstractPlugin.py
moocxing/plugins/sdk/__init__.py
moocxing/robot/Brain.py
moocxing/robot/Config.py
moocxing/robot/Constants.py
moocxing/robot/LoadPlugin.py
moocxing/robot/__init__.py
moocxing/robot/utils/__init__.py
moocxing/robot/utils/serialUtils.py
moocxing/robot/utils/yamlUtils.py
moocxing-1.0.1.dist-info/METADATA
moocxing-1.0.1.dist-info/WHEEL
moocxing-1.0.1.dist-info/top_level.txt
moocxing-1.0.1.dist-info/RECORD
